haystack_integrations/components/embedders/isaacus/__init__.py
haystack_integrations/components/embedders/isaacus/document_embedder.py
haystack_integrations/components/embedders/isaacus/text_embedder.py
haystack_integrations/components/embedders/isaacus/utils.py
haystack_integrations/py.typed
isaacus_haystack-0.1.0.dist-info/METADATA
isaacus_haystack-0.1.0.dist-info/WHEEL
isaacus_haystack-0.1.0.dist-info/licenses/LICENSE
isaacus_haystack-0.1.0.dist-info/RECORD
