Metadata-Version: 2.4
Name: isaacus-haystack
Version: 0.1.0
Summary: Isaacus embedders for Haystack 2.x
Project-URL: Homepage, https://github.com/isaacus-dev/isaacus-haystack
Project-URL: Source, https://github.com/isaacus-dev/isaacus-haystack
Project-URL: Issues, https://github.com/isaacus-dev/isaacus-haystack/issues
Project-URL: Documentation, https://docs.isaacus.com/capabilities/embedding
Author: Isaacus
License: Apache-2.0
License-File: LICENSE
Requires-Python: >=3.9
Requires-Dist: haystack-ai>=2.14.0
Requires-Dist: requests>=2.31.0
